{"shot_Chart_Detail":[{"gridType":"Shot Chart Detail","gameId":"0021900057","gameEventId":744,"playerId":1628413,"playerName":"Jonah Bolden","teamId":1610612755,"teamName":"Philadelphia 76ers","period":4,"minutesRemaining":0,"secondsRemaining":34,"eventType":"Made Shot","actionType":"Running Layup Shot","shotType":"2PT Field Goal","shotZoneBasic":"Restricted Area","shotZoneArea":"Center(C)","shotZoneRange":"Less Than 8 ft.","shotDistance":1,"locX":10,"locY":2,"shotAttemptedFlag":1,"shotMadeFlag":1,"gameDate":"20191030","htm":"PHI","vtm":"MIN"},{"gridType":"Shot Chart Detail","gameId":"0021900641","gameEventId":227,"playerId":1628413,"playerName":"Jonah Bolden","teamId":1610612755,"teamName":"Philadelphia 76ers","period":2,"minutesRemaining":8,"secondsRemaining":22,"eventType":"Made Shot","actionType":"Layup Shot","shotType":"2PT Field Goal","shotZoneBasic":"Restricted Area","shotZoneArea":"Center(C)","shotZoneRange":"Less Than 8 ft.","shotDistance":1,"locX":13,"locY":15,"shotAttemptedFlag":1,"shotMadeFlag":1,"gameDate":"20200120","htm":"BKN","vtm":"PHI"},{"gridType":"Shot Chart Detail","gameId":"0021900641","gameEventId":312,"playerId":1628413,"playerName":"Jonah Bolden","teamId":1610612755,"teamName":"Philadelphia 76ers","period":2,"minutesRemaining":2,"secondsRemaining":39,"eventType":"Missed Shot","actionType":"Jump Shot","shotType":"3PT Field Goal","shotZoneBasic":"Right Corner 3","shotZoneArea":"Right Side(R)","shotZoneRange":"24+ ft.","shotDistance":23,"locX":228,"locY":45,"shotAttemptedFlag":1,"shotMadeFlag":0,"gameDate":"20200120","htm":"BKN","vtm":"PHI"},{"gridType":"Shot Chart Detail","gameId":"0021900815","gameEventId":172,"playerId":1628413,"playerName":"Jonah Bolden","teamId":1610612756,"teamName":"Phoenix Suns","period":2,"minutesRemaining":10,"secondsRemaining":29,"eventType":"Missed Shot","actionType":"Jump Shot","shotType":"3PT Field Goal","shotZoneBasic":"Above the Break 3","shotZoneArea":"Right Side Center(RC)","shotZoneRange":"24+ ft.","shotDistance":25,"locX":111,"locY":235,"shotAttemptedFlag":1,"shotMadeFlag":0,"gameDate":"20200212","htm":"PHX","vtm":"GSW"},{"gridType":"Shot Chart Detail","gameId":"0021900815","gameEventId":178,"playerId":1628413,"playerName":"Jonah Bolden","teamId":1610612756,"teamName":"Phoenix Suns","period":2,"minutesRemaining":10,"secondsRemaining":5,"eventType":"Missed Shot","actionType":"Tip Layup Shot","shotType":"2PT Field Goal","shotZoneBasic":"Restricted Area","shotZoneArea":"Center(C)","shotZoneRange":"Less Than 8 ft.","shotDistance":0,"locX":0,"locY":-6,"shotAttemptedFlag":1,"shotMadeFlag":0,"gameDate":"20200212","htm":"PHX","vtm":"GSW"},{"gridType":"Shot Chart Detail","gameId":"0021900815","gameEventId":290,"playerId":1628413,"playerName":"Jonah Bolden","teamId":1610612756,"teamName":"Phoenix Suns","period":2,"minutesRemaining":2,"secondsRemaining":5,"eventType":"Missed Shot","actionType":"Cutting Dunk Shot","shotType":"2PT Field Goal","shotZoneBasic":"Restricted Area","shotZoneArea":"Center(C)","shotZoneRange":"Less Than 8 ft.","shotDistance":0,"locX":4,"locY":6,"shotAttemptedFlag":1,"shotMadeFlag":0,"gameDate":"20200212","htm":"PHX","vtm":"GSW"},{"gridType":"Shot Chart Detail","gameId":"0021900815","gameEventId":405,"playerId":1628413,"playerName":"Jonah Bolden","teamId":1610612756,"teamName":"Phoenix Suns","period":3,"minutesRemaining":6,"secondsRemaining":28,"eventType":"Made Shot","actionType":"Tip Dunk Shot","shotType":"2PT Field Goal","shotZoneBasic":"Restricted Area","shotZoneArea":"Center(C)","shotZoneRange":"Less Than 8 ft.","shotDistance":2,"locX":-4,"locY":26,"shotAttemptedFlag":1,"shotMadeFlag":1,"gameDate":"20200212","htm":"PHX","vtm":"GSW"},{"gridType":"Shot Chart Detail","gameId":"0021900815","gameEventId":506,"playerId":1628413,"playerName":"Jonah Bolden","teamId":1610612756,"teamName":"Phoenix Suns","period":4,"minutesRemaining":10,"secondsRemaining":1,"eventType":"Missed Shot","actionType":"Layup Shot","shotType":"2PT Field Goal","shotZoneBasic":"Restricted Area","shotZoneArea":"Center(C)","shotZoneRange":"Less Than 8 ft.","shotDistance":0,"locX":-8,"locY":1,"shotAttemptedFlag":1,"shotMadeFlag":0,"gameDate":"20200212","htm":"PHX","vtm":"GSW"},{"gridType":"Shot Chart Detail","gameId":"0021900815","gameEventId":508,"playerId":1628413,"playerName":"Jonah Bolden","teamId":1610612756,"teamName":"Phoenix Suns","period":4,"minutesRemaining":9,"secondsRemaining":57,"eventType":"Made Shot","actionType":"Putback Layup Shot","shotType":"2PT Field Goal","shotZoneBasic":"Restricted Area","shotZoneArea":"Center(C)","shotZoneRange":"Less Than 8 ft.","shotDistance":0,"locX":-4,"locY":0,"shotAttemptedFlag":1,"shotMadeFlag":1,"gameDate":"20200212","htm":"PHX","vtm":"GSW"},{"gridType":"Shot Chart Detail","gameId":"0021900829","gameEventId":708,"playerId":1628413,"playerName":"Jonah Bolden","teamId":1610612756,"teamName":"Phoenix Suns","period":4,"minutesRemaining":0,"secondsRemaining":24,"eventType":"Missed Shot","actionType":"Jump Shot","shotType":"3PT Field Goal","shotZoneBasic":"Above the Break 3","shotZoneArea":"Left Side Center(LC)","shotZoneRange":"24+ ft.","shotDistance":26,"locX":-216,"locY":145,"shotAttemptedFlag":1,"shotMadeFlag":0,"gameDate":"20200221","htm":"TOR","vtm":"PHX"},{"gridType":"Shot Chart Detail","gameId":"0021900839","gameEventId":267,"playerId":1628413,"playerName":"Jonah Bolden","teamId":1610612756,"teamName":"Phoenix Suns","period":2,"minutesRemaining":5,"secondsRemaining":9,"eventType":"Missed Shot","actionType":"Jump Shot","shotType":"3PT Field Goal","shotZoneBasic":"Left Corner 3","shotZoneArea":"Left Side(L)","shotZoneRange":"24+ ft.","shotDistance":22,"locX":-227,"locY":4,"shotAttemptedFlag":1,"shotMadeFlag":0,"gameDate":"20200222","htm":"CHI","vtm":"PHX"}],"leagueAverages":[{"gridType":"League Averages","shotZoneBasic":"Above the Break 3","shotZoneArea":"Back Court(BC)","shotZoneRange":"Back Court Shot","fga":45,"fgm":6,"fgPct":0.133},{"gridType":"League Averages","shotZoneBasic":"Above the Break 3","shotZoneArea":"Center(C)","shotZoneRange":"24+ ft.","fga":14955,"fgm":5168,"fgPct":0.346},{"gridType":"League Averages","shotZoneBasic":"Above the Break 3","shotZoneArea":"Left Side Center(LC)","shotZoneRange":"24+ ft.","fga":20895,"fgm":7459,"fgPct":0.357},{"gridType":"League Averages","shotZoneBasic":"Above the Break 3","shotZoneArea":"Right Side Center(RC)","shotZoneRange":"24+ ft.","fga":19624,"fgm":6875,"fgPct":0.35},{"gridType":"League Averages","shotZoneBasic":"Backcourt","shotZoneArea":"Back Court(BC)","shotZoneRange":"Back Court Shot","fga":405,"fgm":7,"fgPct":0.017},{"gridType":"League Averages","shotZoneBasic":"In The Paint (Non-RA)","shotZoneArea":"Center(C)","shotZoneRange":"8-16 ft.","fga":9820,"fgm":4159,"fgPct":0.424},{"gridType":"League Averages","shotZoneBasic":"In The Paint (Non-RA)","shotZoneArea":"Center(C)","shotZoneRange":"Less Than 8 ft.","fga":16915,"fgm":6518,"fgPct":0.385},{"gridType":"League Averages","shotZoneBasic":"In The Paint (Non-RA)","shotZoneArea":"Left Side(L)","shotZoneRange":"8-16 ft.","fga":1770,"fgm":714,"fgPct":0.403},{"gridType":"League Averages","shotZoneBasic":"In The Paint (Non-RA)","shotZoneArea":"Right Side(R)","shotZoneRange":"8-16 ft.","fga":1871,"fgm":738,"fgPct":0.394},{"gridType":"League Averages","shotZoneBasic":"Left Corner 3","shotZoneArea":"Left Side(L)","shotZoneRange":"24+ ft.","fga":8380,"fgm":3329,"fgPct":0.397},{"gridType":"League Averages","shotZoneBasic":"Mid-Range","shotZoneArea":"Center(C)","shotZoneRange":"8-16 ft.","fga":1778,"fgm":746,"fgPct":0.42},{"gridType":"League Averages","shotZoneBasic":"Mid-Range","shotZoneArea":"Center(C)","shotZoneRange":"16-24 ft.","fga":4036,"fgm":1663,"fgPct":0.412},{"gridType":"League Averages","shotZoneBasic":"Mid-Range","shotZoneArea":"Left Side Center(LC)","shotZoneRange":"16-24 ft.","fga":3634,"fgm":1445,"fgPct":0.398},{"gridType":"League Averages","shotZoneBasic":"Mid-Range","shotZoneArea":"Left Side(L)","shotZoneRange":"16-24 ft.","fga":1541,"fgm":614,"fgPct":0.398},{"gridType":"League Averages","shotZoneBasic":"Mid-Range","shotZoneArea":"Left Side(L)","shotZoneRange":"8-16 ft.","fga":4361,"fgm":1768,"fgPct":0.405},{"gridType":"League Averages","shotZoneBasic":"Mid-Range","shotZoneArea":"Right Side Center(RC)","shotZoneRange":"16-24 ft.","fga":3820,"fgm":1556,"fgPct":0.407},{"gridType":"League Averages","shotZoneBasic":"Mid-Range","shotZoneArea":"Right Side(R)","shotZoneRange":"16-24 ft.","fga":1425,"fgm":561,"fgPct":0.394},{"gridType":"League Averages","shotZoneBasic":"Mid-Range","shotZoneArea":"Right Side(R)","shotZoneRange":"8-16 ft.","fga":4471,"fgm":1792,"fgPct":0.401},{"gridType":"League Averages","shotZoneBasic":"Restricted Area","shotZoneArea":"Center(C)","shotZoneRange":"Less Than 8 ft.","fga":60503,"fgm":38441,"fgPct":0.635},{"gridType":"League Averages","shotZoneBasic":"Right Corner 3","shotZoneArea":"Right Side(R)","shotZoneRange":"24+ ft.","fga":7867,"fgm":2991,"fgPct":0.38}]}